LICENCE.txt
MANIFEST.in
README.rst
setup.py
bin/tree_sisters
tree_sisters/__init__.py
tree_sisters/tree_annotator.py
tree_sisters/version.py
tree_sisters.egg-info/PKG-INFO
tree_sisters.egg-info/SOURCES.txt
tree_sisters.egg-info/dependency_links.txt
tree_sisters.egg-info/requires.txt
tree_sisters.egg-info/top_level.txt