Metadata-Version: 1.0
Name: tree-sisters
Version: 0.0.3
Summary: UNKNOWN
Home-page: UNKNOWN
Author: $AUTHOR
Author-email: UNKNOWN
License: see LICENSE.txt
Platform: UNKNOWN
